bluestackspatcher/LICENSE
bluestackspatcher/README.MD
bluestackspatcher/__init__.py
bluestackspatcher/requirements.txt
bluestackspatcher/thirdparty.json
bluestackspatcher-0.10.dist-info/LICENSE.rst
bluestackspatcher-0.10.dist-info/METADATA
bluestackspatcher-0.10.dist-info/WHEEL
bluestackspatcher-0.10.dist-info/top_level.txt
bluestackspatcher-0.10.dist-info/RECORD
