Metadata-Version: 2.1
Name: bluestackspatcher
Version: 0.10
Summary: Updates IMEI/IMSI on Bluestacks 5.10 / Hyper-V / 64 bit / Android Pie
Home-page: https://github.com/hansalemaos/bluestackspatcher
Author: Johannes Fischer
Author-email: <aulasparticularesdealemaosp@gmail.com>
License: MIT
Keywords: bluestacks,android,adb
Classifier: Development Status :: 4 - Beta
Classifier: Programming Language :: Python :: 3 :: Only
Classifier: Programming Language :: Python :: 3.9
Classifier: Topic :: Scientific/Engineering :: Visualization
Classifier: Topic :: Software Development :: Libraries :: Python Modules
Classifier: Topic :: Text Editors :: Text Processing
Classifier: Topic :: Text Processing :: General
Classifier: Topic :: Text Processing :: Indexing
Classifier: Topic :: Text Processing :: Filters
Classifier: Topic :: Utilities
License-File: LICENSE.rst
Requires-Dist: a-pandas-ex-bstcfg2df
Requires-Dist: bstconnect
Requires-Dist: flatten-everything
Requires-Dist: getdefgateway
Requires-Dist: kthread-sleep
Requires-Dist: pandas
Requires-Dist: pdwinauto
Requires-Dist: PrettyColorPrinter
Requires-Dist: procobserver
Requires-Dist: psutil
Requires-Dist: regex
